<?xml version="1.0" encoding="UTF-8"?>
<bailes>
    <baile>
        <nombre>Tango</nombre>
        <precio moneda="Dolares" couta="Trimestral">75</precio>
        <comienzo>01/02/2024</comienzo>
        <fin>20/02/2024</fin>
        <profesor>Juan luis</profesor>
        <sala>103</sala>
        <plaza>15</plaza>
    </baile>
    <baile>
        <nombre>Salsa</nombre>
        <precio moneda="Dolares" couta="Trimestral">75</precio>
        <comienzo>01/02/2024</comienzo>
        <fin>20/02/2024</fin>
        <profesor>juan luis</profesor>
        <sala>109</sala>
        <plaza>15</plaza>
    </baile>
</bailes>